README.rst
setup.py
typecheck/__init__.py
typecheck/decorators.py
typecheck/framework.py
typecheck/tc_predicates.py
typecheck/test_new.py
typecheck/test_tc_predicates.py
typecheck/test_typecheck_basics.py
typecheck/test_typing_annotations.py
typecheck/testhelper.py
typecheck/typing_predicates.py
typecheck_decorator.egg-info/PKG-INFO
typecheck_decorator.egg-info/SOURCES.txt
typecheck_decorator.egg-info/dependency_links.txt
typecheck_decorator.egg-info/requires.txt
typecheck_decorator.egg-info/top_level.txt