Metadata-Version: 1.1
Name: typecheck-decorator
Version: 1.3
Summary: flexible explicit run-time type checking of function arguments (Python3-only)
Home-page: http://github.com/prechelt/typecheck-decorator
Author: Dmitry Dvoinikov, Lutz Prechelt
Author-email: prechelt@inf.fu-berlin.de
License: BSD License
Keywords: type-checking
Platform: UNKNOWN
Classifier: License :: OSI Approved :: BSD License
Classifier: Development Status :: 5 - Production/Stable
Classifier: Intended Audience :: Developers
Classifier: Topic :: Software Development :: Quality Assurance
Classifier: Topic :: Software Development :: Documentation
Classifier: Programming Language :: Python :: 3
Classifier: Programming Language :: Python :: 3.3
Classifier: Programming Language :: Python :: 3.4
Classifier: Programming Language :: Python :: 3.5
